{
  "name": "Tentacules absorbeur de magie",
  "type": "weapon",
  "flags": {},
  "img": "icons/magic/water/tendrils-ice-growth.webp",
  "_id": "ckqFv5x9s2l8EXPY",
  "system": {
    "description": {
      "value": "<p><strong>Tentacule absorbeur de magie.</strong> Attaque au corps à corps sur une cible. Un objet magique de la cible est agrippé et peut perdre ses facultés magiques temporairement ou définitivement.</p>",
      "chat": "",
      "unidentified": ""
    },
    "source": "Créatures et Oppositions",
    "quantity": 1,
    "weight": 0,
    "price": 0,
    "attunement": 0,
    "equipped": false,
    "rarity": "",
    "identified": true,
    "activation": {
      "type": "action",
      "cost": 1,
      "condition": ""
    },
    "duration": {
      "value": null,
      "units": ""
    },
    "target": {
      "value": 1,
      "width": null,
      "units": "any",
      "type": ""
    },
    "range": {
      "value": 4.5,
      "long": null,
      "units": "m"
    },
    "uses": {
      "value": null,
      "max": 0,
      "per": "",
      "recovery": ""
    },
    "consume": {
      "type": "",
      "target": "",
      "amount": null
    },
    "ability": "",
    "actionType": "mwak",
    "attackBonus": 0,
    "chatFlavor": "",
    "critical": {
      "threshold": null,
      "damage": null
    },
    "damage": {
      "parts": [],
      "versatile": ""
    },
    "formula": "",
    "save": {
      "ability": "",
      "dc": null,
      "scaling": "spell"
    },
    "armor": {
      "value": 10
    },
    "hp": {
      "value": 0,
      "max": 0,
      "dt": null,
      "conditions": ""
    },
    "weaponType": "natural",
    "baseItem": "",
    "properties": {
      "two": false,
      "rch": false,
      "lod": false,
      "fir": false,
      "fin": false,
      "foc": false,
      "thr": false,
      "lgt": false,
      "hvy": false,
      "amm": false,
      "ver": false,
      "rel": false,
      "ret": false,
      "spc": false
    },
    "proficient": true
  },
  "ownership": {
    "default": 0
  },
  "effects": [],
  "folder": null,
  "sort": 0,
  "_stats": {
    "systemId": "dnd5e",
    "systemVersion": "2.0.3",
    "coreVersion": "10.286",
    "createdTime": 1663923698886,
    "modifiedTime": 1663923699847,
    "lastModifiedBy": "packsbuilder0000"
  },
  "_key": "!items!ckqFv5x9s2l8EXPY"
}
